COPYING
COPYING.lesser
MANIFEST.in
NOTICE
README.md
requirements.txt
setup.py
TCgram/__init__.py
TCgram/client.py
TCgram/dispatcher.py
TCgram/emoji.py
TCgram/file_id.py
TCgram/filters.py
TCgram/mime_types.py
TCgram/py.typed
TCgram/sync.py
TCgram/utils.py
TCgram.egg-info/PKG-INFO
TCgram.egg-info/SOURCES.txt
TCgram.egg-info/dependency_links.txt
TCgram.egg-info/not-zip-safe
TCgram.egg-info/requires.txt
TCgram.egg-info/top_level.txt
TCgram/connection/__init__.py
TCgram/connection/connection.py
TCgram/connection/transport/__init__.py
TCgram/connection/transport/tcp/__init__.py
TCgram/connection/transport/tcp/tcp.py
TCgram/connection/transport/tcp/tcp_abridged.py
TCgram/connection/transport/tcp/tcp_abridged_o.py
TCgram/connection/transport/tcp/tcp_full.py
TCgram/connection/transport/tcp/tcp_intermediate.py
TCgram/connection/transport/tcp/tcp_intermediate_o.py
TCgram/crypto/__init__.py
TCgram/crypto/aes.py
TCgram/crypto/mtproto.py
TCgram/crypto/prime.py
TCgram/crypto/rsa.py
TCgram/enums/__init__.py
TCgram/enums/auto_name.py
TCgram/enums/chat_action.py
TCgram/enums/chat_event_action.py
TCgram/enums/chat_member_status.py
TCgram/enums/chat_members_filter.py
TCgram/enums/chat_type.py
TCgram/enums/message_entity_type.py
TCgram/enums/message_media_type.py
TCgram/enums/message_service_type.py
TCgram/enums/messages_filter.py
TCgram/enums/next_code_type.py
TCgram/enums/parse_mode.py
TCgram/enums/poll_type.py
TCgram/enums/sent_code_type.py
TCgram/enums/user_status.py
TCgram/errors/__init__.py
TCgram/errors/rpc_error.py
TCgram/handlers/__init__.py
TCgram/handlers/callback_query_handler.py
TCgram/handlers/chat_join_request_handler.py
TCgram/handlers/chat_member_updated_handler.py
TCgram/handlers/chosen_inline_result_handler.py
TCgram/handlers/deleted_messages_handler.py
TCgram/handlers/disconnect_handler.py
TCgram/handlers/edited_message_handler.py
TCgram/handlers/handler.py
TCgram/handlers/inline_query_handler.py
TCgram/handlers/message_handler.py
TCgram/handlers/poll_handler.py
TCgram/handlers/raw_update_handler.py
TCgram/handlers/user_status_handler.py
TCgram/methods/__init__.py
TCgram/methods/advanced/__init__.py
TCgram/methods/advanced/invoke.py
